yoyo_indexima/__init__.py
yoyo_indexima/__main__.py
yoyo_indexima/backend.py
yoyo_indexima/cli/__init__.py
yoyo_indexima/cli/breaklock_cmd.py
yoyo_indexima/cli/common.py
yoyo_indexima/cli/migration_cmd.py
yoyo_indexima/cli/parser.py
yoyo_indexima/connections.py
yoyo_indexima/internalmigrations/__init__.py
yoyo_indexima/internalmigrations/v1.py
yoyo_indexima/internalmigrations/v2.py
yoyo_indexima/logger.py
yoyo_indexima-0.1.3.dist-info/entry_points.txt
yoyo_indexima-0.1.3.dist-info/LICENSE.md
yoyo_indexima-0.1.3.dist-info/WHEEL
yoyo_indexima-0.1.3.dist-info/METADATA
yoyo_indexima-0.1.3.dist-info/RECORD
