Metadata-Version: 2.1
Name: yoyo-indexima
Version: 0.1.3
Summary: Indexima migration schema based on yoyo
Home-page: https://pypi.org/project/yoyo_indexima
License: MIT
Author: Jerome Guibert
Author-email: jguibert@gmail.com
Requires-Python: >=3.7,<4.0
Classifier: Development Status :: 5 - Production/Stable
Classifier: Intended Audience :: Developers
Classifier: License :: OSI Approved :: MIT License
Classifier: Natural Language :: English
Classifier: Programming Language :: Python
Classifier: Programming Language :: Python :: 3
Classifier: Programming Language :: Python :: 3.7
Classifier: Topic :: Software Development :: Libraries :: Python Modules
Classifier: Typing :: Typed
Requires-Dist: PyHive (==0.6.1)
Requires-Dist: crayons (==0.3.0)
Requires-Dist: thrift (==0.13.0)
Requires-Dist: thrift-sasl
Requires-Dist: yoyo-migrations (>=6.1.0,<6.2.0)
Project-URL: Documentation, https://geronimo-iia.github.io/yoyo-indexima/
Project-URL: Repository, https://github.com/geronimo-iia/yoyo-indexima
